Workbook

Sheet Read me
A1: Northbridge Supplies: UAT test plan
A3: What this is | B3: User acceptance testing (UAT) for the new invoice approval process. Real users test it before go-live, to confirm it works the way the requirements say. Each test case comes from an acceptance criterion in the requirements spreadsheet.
A4: Author | B4: Felicia Oyebode, Business Analyst
A5: In scope | B5: Phase A and Phase B stories (US01 to US10, and US12). Phase C (US11) will be tested in its own project. Won't-have stories (US13, US14) are not tested.
A7: How to use it | B7: Testers fill in the yellow columns on the Test cases tab: the date tested, Pass / Fail / Blocked, what actually happened, and any defect number. The Summary tab updates by itself.
A9: Ready to start testing when
A10: 1 | B10: The workflow module is set up in a test copy of the finance system
A11: 2 | B11: The approval list and backup approvers are loaded
A12: 3 | B12: Testers have had a short walkthrough
A14: Ready to go live when
A15: 1 | B15: Every Must-have test has passed
A16: 2 | B16: No open high-priority defects
A17: 3 | B17: Helen Marsh signs off
A19: Testers | B19: AP clerk, AP team lead (Daniel Okafor), Operations Manager (Mark Reid), Marketing Manager, Operations supervisor, Procurement lead, Financial Controller, Finance Director (Helen Marsh), Finance owner
A21: Note | B21: Test data uses real examples from the 2025 invoice data where useful. Northbridge Supplies is a fictional company. This is a portfolio case study.

Sheet Test cases
A1: Test ID | B1: Story | C1: What we're testing | D1: Steps | E1: Test data | F1: Expected result | G1: Tester | H1: Date tested | I1: Result | J1: What actually happened | K1: Defect ref
A2: TC01 | B2: US01 | C2: Exact duplicate is blocked | D2: 1. Log an invoice from Albion Packaging Ltd with invoice number 001-13797. 2. Log the same invoice again. | E2: Albion Packaging Ltd, 001-13797, £1,979.70 (one of the 2025 duplicates) | F2: Second invoice is blocked from payment. AP gets an alert with a link to the first one. | G2: AP clerk | I2: Not run
A3: TC02 | B3: US01 | C3: Near-duplicate with different punctuation is blocked | D3: 1. Log invoice 004-10261 from Dunmore Packaging Ltd. 2. Log the same invoice with the number typed as 004 10261. | E3: Dunmore Packaging Ltd, 004-10261, £310.42 | F3: Second invoice is treated as a duplicate and blocked. | G3: AP clerk | I3: Not run
A4: TC03 | B4: US01 | C4: Only the Financial Controller can release a blocked invoice | D4: 1. As an AP clerk, try to release a blocked invoice. 2. As the Financial Controller, release it without a reason. 3. Release it again, this time with a reason. | E4: Any blocked invoice from the tests above | F4: AP clerk cannot release it. Financial Controller cannot release it without a reason. With a reason, it is released and the reason is saved. | G4: AP clerk, Financial Controller | I4: Not run
A5: TC04 | B5: US01 | C5: Different invoice from the same supplier is not blocked | D5: 1. Log a new invoice from Albion Packaging Ltd with a different invoice number. | E5: Albion Packaging Ltd, new invoice number | F5: Invoice is accepted as normal. No duplicate alert. | G5: AP clerk | I5: Not run
A6: TC05 | B6: US02 | C6: Duplicate payments list is complete | D6: 1. Open the list of 2025 duplicate payments. 2. Add up the amounts and count the lines. | E6: 2025 duplicates list | F6: List shows supplier, invoice number, amount and both payment dates. 45 invoices totalling £158,776. | G6: Financial Controller | I6: Not run
A7: TC06 | B7: US02 | C7: Recovery status can be tracked | D7: 1. Pick one line on the list. 2. Change its status to 'Requested', then 'Agreed', then 'Received'. | E7: Any line on the list | F7: Each status saves and shows on the list. | G7: Financial Controller | I7: Not run
A8: TC07 | B8: US03 | C8: Invoice with no PO is returned to the supplier | D8: 1. Log an invoice with no PO number. 2. Return it using the standard email. | E8: Test invoice with blank PO field | F8: Standard email goes to the supplier within 1 working day. Invoice shows as 'returned: no PO'. | G8: AP clerk | I8: Not run
A9: TC08 | B9: US03 | C9: Resent invoice with a valid PO goes through normally | D9: 1. Log the returned invoice again, now with a valid PO number. | E9: Same supplier and amount, valid PO added | F9: Invoice goes through the normal process. It is not flagged as a duplicate of the returned one. | G9: AP clerk | I9: Not run
A10: TC09 | B10: US04 | C10: Emergency PO can be raised quickly on a phone | D10: 1. On a phone, open the emergency PO form. 2. Enter supplier, description, rough cost and cost centre. 3. Submit and time it. | E10: Forklift repair, about £850, Operations cost centre | F10: Only those four fields are needed. A PO number appears straight away. Takes under 2 minutes. | G10: Operations supervisor | I10: Not run
A11: TC10 | B11: US04 | C11: Budget holder is told about the emergency PO | D11: 1. Raise an emergency PO as above. 2. Check the budget holder's notifications. | E11: As above | F11: Budget holder is notified with the PO details. | G11: Operations Manager | I11: Not run
A12: TC11 | B12: US04 | C12: Monthly list of emergency POs is produced | D12: 1. Raise three emergency POs during the test period. 2. Run the month-end emergency PO list. | E12: Three test emergency POs | F12: All three appear on the list with who raised them, supplier and amount. | G12: Financial Controller | I12: Not run
A13: TC12 | B13: US05 | C13: Supplier notice reaches all regular suppliers | D13: 1. Get the list of suppliers invoiced in the last 12 months. 2. Check it against the list the notice was sent to. | E13: Supplier list and notice mailing list | F13: Every supplier on the 12-month list received the notice. Notice names a Procurement contact. | G13: Procurement lead | I13: Not run
... A31: TC30 | B31: US12 | C31: Controls figures are shown | D31: 1. Open the controls view. | E31: Test month's data | F31: Shows duplicates blocked, invoices returned for no PO, and open queries. Each matches the test log. | G31: Finance Director | I31: Not run

Sheet Summary
A1: Test progress
A3: Result | B3: Test cases | C3: Share
A4: Pass | B4: =COUNTIF('Test cases'!$I$2:$I$31,A4) -> 0 | C4: =IFERROR(B4/$B$8,0) -> 0
A5: Fail | B5: =COUNTIF('Test cases'!$I$2:$I$31,A5) -> 0 | C5: =IFERROR(B5/$B$8,0) -> 0
A6: Blocked | B6: =COUNTIF('Test cases'!$I$2:$I$31,A6) -> 0 | C6: =IFERROR(B6/$B$8,0) -> 0
A7: Not run | B7: =COUNTIF('Test cases'!$I$2:$I$31,A7) -> 30 | C7: =IFERROR(B7/$B$8,0) -> 1
A8: Total | B8: =SUM(B4:B7) -> 30 | C8: =SUM(C4:C7) -> 1
A10: Ready to go live? | B10: =IF(AND(B5=0,B6=0,B7=0,B8>0),"Yes, if Helen signs off","Not yet") -> Not yet
A11: Rule: every test passed, none failed, blocked or not run, and no open high-priority defects.
A13: By story
A14: Story | B14: Test cases | C14: Passed | D14: Failed
A15: US01 | B15: =COUNTIF('Test cases'!$B$2:$B$31,A15) -> 4 | C15: =COUNTIFS('Test cases'!$B$2:$B$31,A15,'Test cases'!$I$2:$I$31,"Pass") -> 0 | D15: =COUNTIFS('Test cases'!$B$2:$B$31,A15,'Test cases'!$I$2:$I$31,"Fail") -> 0
A16: US02 | B16: =COUNTIF('Test cases'!$B$2:$B$31,A16) -> 2 | C16: =COUNTIFS('Test cases'!$B$2:$B$31,A16,'Test cases'!$I$2:$I$31,"Pass") -> 0 | D16: =COUNTIFS('Test cases'!$B$2:$B$31,A16,'Test cases'!$I$2:$I$31,"Fail") -> 0
A17: US03 | B17: =COUNTIF('Test cases'!$B$2:$B$31,A17) -> 2 | C17: =COUNTIFS('Test cases'!$B$2:$B$31,A17,'Test cases'!$I$2:$I$31,"Pass") -> 0 | D17: =COUNTIFS('Test cases'!$B$2:$B$31,A17,'Test cases'!$I$2:$I$31,"Fail") -> 0
A18: US04 | B18: =COUNTIF('Test cases'!$B$2:$B$31,A18) -> 3 | C18: =COUNTIFS('Test cases'!$B$2:$B$31,A18,'Test cases'!$I$2:$I$31,"Pass") -> 0 | D18: =COUNTIFS('Test cases'!$B$2:$B$31,A18,'Test cases'!$I$2:$I$31,"Fail") -> 0
A19: US05 | B19: =COUNTIF('Test cases'!$B$2:$B$31,A19) -> 1 | C19: =COUNTIFS('Test cases'!$B$2:$B$31,A19,'Test cases'!$I$2:$I$31,"Pass") -> 0 | D19: =COUNTIFS('Test cases'!$B$2:$B$31,A19,'Test cases'!$I$2:$I$31,"Fail") -> 0
A20: US06 | B20: =COUNTIF('Test cases'!$B$2:$B$31,A20) -> 4 | C20: =COUNTIFS('Test cases'!$B$2:$B$31,A20,'Test cases'!$I$2:$I$31,"Pass") -> 0 | D20: =COUNTIFS('Test cases'!$B$2:$B$31,A20,'Test cases'!$I$2:$I$31,"Fail") -> 0
A21: US07 | B21: =COUNTIF('Test cases'!$B$2:$B$31,A21) -> 3 | C21: =COUNTIFS('Test cases'!$B$2:$B$31,A21,'Test cases'!$I$2:$I$31,"Pass") -> 0 | D21: =COUNTIFS('Test cases'!$B$2:$B$31,A21,'Test cases'!$I$2:$I$31,"Fail") -> 0
A22: US08 | B22: =COUNTIF('Test cases'!$B$2:$B$31,A22) -> 3 | C22: =COUNTIFS('Test cases'!$B$2:$B$31,A22,'Test cases'!$I$2:$I$31,"Pass") -> 0 | D22: =COUNTIFS('Test cases'!$B$2:$B$31,A22,'Test cases'!$I$2:$I$31,"Fail") -> 0
A23: US09 | B23: =COUNTIF('Test cases'!$B$2:$B$31,A23) -> 2 | C23: =COUNTIFS('Test cases'!$B$2:$B$31,A23,'Test cases'!$I$2:$I$31,"Pass") -> 0 | D23: =COUNTIFS('Test cases'!$B$2:$B$31,A23,'Test cases'!$I$2:$I$31,"Fail") -> 0
A24: US10 | B24: =COUNTIF('Test cases'!$B$2:$B$31,A24) -> 3 | C24: =COUNTIFS('Test cases'!$B$2:$B$31,A24,'Test cases'!$I$2:$I$31,"Pass") -> 0 | D24: =COUNTIFS('Test cases'!$B$2:$B$31,A24,'Test cases'!$I$2:$I$31,"Fail") -> 0
A25: US12 | B25: =COUNTIF('Test cases'!$B$2:$B$31,A25) -> 3 | C25: =COUNTIFS('Test cases'!$B$2:$B$31,A25,'Test cases'!$I$2:$I$31,"Pass") -> 0 | D25: =COUNTIFS('Test cases'!$B$2:$B$31,A25,'Test cases'!$I$2:$I$31,"Fail") -> 0
